semdb_library/__init__.py
semdb_library/connection.py
semdb_library/model.py
semdb_library-0.9.6.11.dist-info/LICENSE.txt
semdb_library-0.9.6.11.dist-info/METADATA
semdb_library-0.9.6.11.dist-info/WHEEL
semdb_library-0.9.6.11.dist-info/top_level.txt
semdb_library-0.9.6.11.dist-info/RECORD
