Metadata-Version: 2.1
Name: semdb-library
Version: 0.9.6.11
Requires-Python: >=3.7, <4
License-File: LICENSE.txt
Requires-Dist: requests
Requires-Dist: numpy
